README.txt
setup.py
met/__init__.py
met/agrimet.py
met/eddy_flux.py
met/elevation.py
met/fao.py
met/lathuille_variables.py
met/thredds.py
metio.egg-info/PKG-INFO
metio.egg-info/SOURCES.txt
metio.egg-info/dependency_links.txt
metio.egg-info/requires.txt
metio.egg-info/top_level.txt