Metadata-Version: 1.1
Name: metio
Version: 0.0.22
Summary: Very simple API to download gridded meteorology data from the web
Home-page: https://github.com/dgketchum/metio
Author: David Ketchum
Author-email: dgketchum@gmail.com
License: Apache
Download-URL: https://github.com/dgketchum/Metio/archive/0.0.22.tar.gz
Keywords: landsat gridded meteorology hydrology remote sensing
Platform: Posix; MacOS X; Windows
Classifier: Intended Audience :: Science/Research
Classifier: Topic :: Scientific/Engineering :: GIS
Classifier: License :: OSI Approved :: Apache Software License
Classifier: Programming Language :: Python :: 2.7
Classifier: Programming Language :: Python :: 3.6
